nhnscan/__init__.py
nhnscan/__main__.py
nhnscan/base.py
nhnscan/cli.py
nhnscan/scanners/__init__.py
nhnscan/scanners/nmap_scanner.py
nhnscan/scanners/snmp_scanner.py
nhnscan-0.1.1.dist-info/METADATA
nhnscan-0.1.1.dist-info/WHEEL
nhnscan-0.1.1.dist-info/entry_points.txt
nhnscan-0.1.1.dist-info/top_level.txt
nhnscan-0.1.1.dist-info/RECORD
