Metadata-Version: 2.4
Name: nhnscan
Version: 0.1.1
Summary: Security Scanner - CLI wrapper for nmap and snmpwalk
Author: David
Author-email: David <topcremaa@gmail.com>
Project-URL: Homepage, https://github.com/topcrema
Project-URL: Issues, https://github.com/topcrema
Keywords: security,scanner,nmap,snmp
Classifier: Programming Language :: Python :: 3
Classifier: Operating System :: POSIX :: Linux
Requires-Python: >=3.7
Dynamic: author
Dynamic: requires-python
